tsnmf/__init__.py
tsnmf/model_selection.py
tsnmf/tsnmf.py
tsnmf/version.py
tsnmf/data/output.mat
tsnmf/data/sonar_output.mat
tsnmf/tests/__init__.py
tsnmf/tests/test_smoothNMF.py
time_series_nmf-0.1.0.dev0.dist-info/LICENSE.md
time_series_nmf-0.1.0.dev0.dist-info/METADATA
time_series_nmf-0.1.0.dev0.dist-info/WHEEL
time_series_nmf-0.1.0.dev0.dist-info/top_level.txt
time_series_nmf-0.1.0.dev0.dist-info/RECORD
