Metadata-Version: 2.1
Name: time-series-nmf
Version: 0.1.0.dev0
Summary: Time Series NMF
Home-page: https://github.com/valentina-s/time-series-nmf
Author: Valentina Staneva
Author-email: vms16@uw.edu
Maintainer: Valentina Staneva
Maintainer-email: vms16@uw.edu
License: MIT License
Platform: UNKNOWN
Requires-Dist: scipy
Requires-Dist: numpy
